globaltrie/__init__.py
globaltrie/__main__.py
globaltrie/client_class.py
globaltrie/client_cli.py
globaltrie-1.0.5.dist-info/METADATA
globaltrie-1.0.5.dist-info/WHEEL
globaltrie-1.0.5.dist-info/entry_points.txt
globaltrie-1.0.5.dist-info/top_level.txt
globaltrie-1.0.5.dist-info/RECORD
